{
  "id": "boofy",
  "name": "Boofy",
  "bookName": "BOOFY SPORTSBOOK",
  "tagline": "Official betting partner of Boofy",
  "stakes": {
    "buyIn": "$20",
    "pot": "$260",
    "payouts": [
      "1st $200",
      "2nd $40",
      "3rd $20"
    ]
  },
  "copy": {
    "outright": "First place takes $200 even — Dante topped up the pot. Dead-heat rules: ties split the cash.",
    "toCash": "Twelve seats, three podium spots. Any money is good money.",
    "spoon": "Somebody has to carry the shame until 2030.",
    "h2h": "The four strongest seats, priced against each other. Higher pool finish wins; tie on points = stakes returned (handled as half-win in pricing).",
    "watch": "Germany, Brazil, South Korea, Netherlands — the house's problem child drew a loaded hand. The model's median is 8 points. Main line:"
  },
  "meta": {
    "sims": 400000,
    "generated": "2026-07-02",
    "date": "2026-07-02",
    "seed": null,
    "sources": "LIVE MARKET CONSENSUS",
    "consensusDate": "2026-07-02",
    "consensusSource": "kalshi:KXMENWORLDCUP-26",
    "matchesConditioned": 85,
    "calibrationErr": 0.0192,
    "players": 12,
    "teamsPerPlayer": 4
  },
  "outright": [
    {
      "player": "Rob",
      "teams": [
        "Tunisia",
        "Iraq",
        "England",
        "France"
      ],
      "price": "−115",
      "fairPct": 39.9
    },
    {
      "player": "Nathan",
      "teams": [
        "Argentina",
        "South Africa",
        "Croatia",
        "Egypt"
      ],
      "price": "+270",
      "fairPct": 20.2
    },
    {
      "player": "Max",
      "teams": [
        "Norway",
        "Ghana",
        "United States",
        "Senegal"
      ],
      "price": "+520",
      "fairPct": 11.9
    },
    {
      "player": "Dino",
      "teams": [
        "Iran",
        "Portugal",
        "Canada",
        "Morocco"
      ],
      "price": "+560",
      "fairPct": 11.2
    },
    {
      "player": "Jake",
      "teams": [
        "Qatar",
        "Switzerland",
        "Mexico",
        "New Zealand"
      ],
      "price": "+1350",
      "fairPct": 5.1
    },
    {
      "player": "Kunal",
      "teams": [
        "Germany",
        "Brazil",
        "South Korea",
        "Netherlands"
      ],
      "price": "+1400",
      "fairPct": 5
    },
    {
      "player": "Jack",
      "teams": [
        "Colombia",
        "Australia",
        "Austria",
        "Uruguay"
      ],
      "price": "+2750",
      "fairPct": 2.6
    },
    {
      "player": "Dante",
      "teams": [
        "Scotland",
        "Spain",
        "Türkiye",
        "Saudi Arabia"
      ],
      "price": "+3000",
      "fairPct": 2.4
    },
    {
      "player": "Nick",
      "teams": [
        "Japan",
        "DR Congo",
        "Bosnia & Herzegovina",
        "Belgium"
      ],
      "price": "+5300",
      "fairPct": 1.4
    },
    {
      "player": "Adrian",
      "teams": [
        "Sweden",
        "Cape Verde",
        "Paraguay",
        "Jordan"
      ],
      "price": "+24000",
      "fairPct": 0.3
    },
    {
      "player": "Matt",
      "teams": [
        "Panama",
        "Uzbekistan",
        "Curaçao",
        "Haiti"
      ],
      "price": null,
      "fairPct": 0,
      "status": "dead"
    },
    {
      "player": "Shaya",
      "teams": [
        "Ecuador",
        "Czechia",
        "Ivory Coast",
        "Algeria"
      ],
      "price": null,
      "fairPct": 0,
      "status": "dead"
    }
  ],
  "toCash": [
    {
      "player": "Dino",
      "teams": [
        "Iran",
        "Portugal",
        "Canada",
        "Morocco"
      ],
      "price": "−810",
      "fairPct": 71.2
    },
    {
      "player": "Max",
      "teams": [
        "Norway",
        "Ghana",
        "United States",
        "Senegal"
      ],
      "price": "−420",
      "fairPct": 64.5
    },
    {
      "player": "Rob",
      "teams": [
        "Tunisia",
        "Iraq",
        "England",
        "France"
      ],
      "price": "−280",
      "fairPct": 59
    },
    {
      "player": "Nathan",
      "teams": [
        "Argentina",
        "South Africa",
        "Croatia",
        "Egypt"
      ],
      "price": "−210",
      "fairPct": 54.5
    },
    {
      "player": "Jake",
      "teams": [
        "Qatar",
        "Switzerland",
        "Mexico",
        "New Zealand"
      ],
      "price": "+510",
      "fairPct": 13
    },
    {
      "player": "Jack",
      "teams": [
        "Colombia",
        "Australia",
        "Austria",
        "Uruguay"
      ],
      "price": "+630",
      "fairPct": 11
    },
    {
      "player": "Kunal",
      "teams": [
        "Germany",
        "Brazil",
        "South Korea",
        "Netherlands"
      ],
      "price": "+750",
      "fairPct": 9.4
    },
    {
      "player": "Dante",
      "teams": [
        "Scotland",
        "Spain",
        "Türkiye",
        "Saudi Arabia"
      ],
      "price": "+810",
      "fairPct": 8.8
    },
    {
      "player": "Nick",
      "teams": [
        "Japan",
        "DR Congo",
        "Bosnia & Herzegovina",
        "Belgium"
      ],
      "price": "+1150",
      "fairPct": 6.4
    },
    {
      "player": "Adrian",
      "teams": [
        "Sweden",
        "Cape Verde",
        "Paraguay",
        "Jordan"
      ],
      "price": "+3400",
      "fairPct": 2.3
    },
    {
      "player": "Matt",
      "teams": [
        "Panama",
        "Uzbekistan",
        "Curaçao",
        "Haiti"
      ],
      "price": null,
      "fairPct": 0,
      "status": "dead"
    },
    {
      "player": "Shaya",
      "teams": [
        "Ecuador",
        "Czechia",
        "Ivory Coast",
        "Algeria"
      ],
      "price": null,
      "fairPct": 0,
      "status": "dead"
    }
  ],
  "spoon": [
    {
      "player": "Matt",
      "teams": [
        "Panama",
        "Uzbekistan",
        "Curaçao",
        "Haiti"
      ],
      "price": null,
      "fairPct": 100,
      "status": "locked"
    },
    {
      "player": "Nick",
      "teams": [
        "Japan",
        "DR Congo",
        "Bosnia & Herzegovina",
        "Belgium"
      ],
      "price": null,
      "fairPct": 0,
      "status": "dead"
    },
    {
      "player": "Jack",
      "teams": [
        "Colombia",
        "Australia",
        "Austria",
        "Uruguay"
      ],
      "price": null,
      "fairPct": 0,
      "status": "dead"
    },
    {
      "player": "Dante",
      "teams": [
        "Scotland",
        "Spain",
        "Türkiye",
        "Saudi Arabia"
      ],
      "price": null,
      "fairPct": 0,
      "status": "dead"
    },
    {
      "player": "Jake",
      "teams": [
        "Qatar",
        "Switzerland",
        "Mexico",
        "New Zealand"
      ],
      "price": null,
      "fairPct": 0,
      "status": "dead"
    },
    {
      "player": "Dino",
      "teams": [
        "Iran",
        "Portugal",
        "Canada",
        "Morocco"
      ],
      "price": null,
      "fairPct": 0,
      "status": "dead"
    },
    {
      "player": "Adrian",
      "teams": [
        "Sweden",
        "Cape Verde",
        "Paraguay",
        "Jordan"
      ],
      "price": null,
      "fairPct": 0,
      "status": "dead"
    },
    {
      "player": "Max",
      "teams": [
        "Norway",
        "Ghana",
        "United States",
        "Senegal"
      ],
      "price": null,
      "fairPct": 0,
      "status": "dead"
    },
    {
      "player": "Rob",
      "teams": [
        "Tunisia",
        "Iraq",
        "England",
        "France"
      ],
      "price": null,
      "fairPct": 0,
      "status": "dead"
    },
    {
      "player": "Shaya",
      "teams": [
        "Ecuador",
        "Czechia",
        "Ivory Coast",
        "Algeria"
      ],
      "price": null,
      "fairPct": 0,
      "status": "dead"
    },
    {
      "player": "Kunal",
      "teams": [
        "Germany",
        "Brazil",
        "South Korea",
        "Netherlands"
      ],
      "price": null,
      "fairPct": 0,
      "status": "dead"
    },
    {
      "player": "Nathan",
      "teams": [
        "Argentina",
        "South Africa",
        "Croatia",
        "Egypt"
      ],
      "price": null,
      "fairPct": 0,
      "status": "dead"
    }
  ],
  "h2h": [
    {
      "a": "Dino",
      "b": "Rob",
      "priceA": "−100",
      "priceB": "−135"
    },
    {
      "a": "Dino",
      "b": "Max",
      "priceA": "−130",
      "priceB": "−105"
    },
    {
      "a": "Dino",
      "b": "Nathan",
      "priceA": "−160",
      "priceB": "+120"
    },
    {
      "a": "Rob",
      "b": "Max",
      "priceA": "−140",
      "priceB": "+100"
    },
    {
      "a": "Rob",
      "b": "Nathan",
      "priceA": "−165",
      "priceB": "+120"
    },
    {
      "a": "Max",
      "b": "Nathan",
      "priceA": "−140",
      "priceB": "+105"
    }
  ],
  "grudges": {
    "title": "BAD BLOOD — GRUDGE MATCHES",
    "blurb": "Some matchups are about money. These are not. Higher pool finish settles it; tie on points = stakes returned, beef continues.",
    "pairs": [
      {
        "a": "Shaya",
        "b": "Jake",
        "note": "THE FOREVER FEUD",
        "priceA": null,
        "priceB": null,
        "settled": "b"
      },
      {
        "a": "Shaya",
        "b": "Matt",
        "note": "YES, SHAYA AGAIN",
        "priceA": null,
        "priceB": null,
        "settled": "a"
      }
    ]
  },
  "caleb": {
    "title": "CALEB'S CORNER — DEGEN SPECIALS",
    "blurb": "Caleb is not in the pool. That has never once stopped him. The house posts the slips he'd actually ask for, and reserves the right to demand cash up front.",
    "bets": [
      {
        "label": "Matt wins the whole pool (Panama · Uzbekistan · Curaçao · Haiti)",
        "price": null
      },
      {
        "label": "Matt cashes top 3",
        "price": null
      },
      {
        "label": "Shaya sweeps the beef — finishes above Jake AND Matt",
        "price": null
      },
      {
        "label": "Kunal goes nuclear — Over 14.5 pts",
        "price": null
      },
      {
        "label": "Rob bricks it — Under 4.5 pts with England AND France",
        "price": "+2100"
      }
    ]
  },
  "watch": {
    "player": "Kunal",
    "title": "KUNAL WATCH — KUNAL TOTAL POINTS",
    "teams": [
      "Germany",
      "Brazil",
      "South Korea",
      "Netherlands"
    ],
    "median": 5,
    "mainLine": 4.5,
    "ladder": [
      {
        "line": 4.5,
        "over": "−195",
        "under": "+140"
      },
      {
        "line": 5.5,
        "over": "+210",
        "under": "−310"
      },
      {
        "line": 6.5,
        "over": "+520",
        "under": "−1050"
      },
      {
        "line": 7.5,
        "over": "+1450",
        "under": "−2400"
      },
      {
        "line": 8.5,
        "over": "+1450",
        "under": "−2400"
      },
      {
        "line": 9.5,
        "over": "+1450",
        "under": "−2400"
      }
    ],
    "hist": [
      {
        "pts": 0,
        "pct": 0
      },
      {
        "pts": 1,
        "pct": 0
      },
      {
        "pts": 2,
        "pct": 0
      },
      {
        "pts": 3,
        "pct": 0
      },
      {
        "pts": 4,
        "pct": 38.36
      },
      {
        "pts": 5,
        "pct": 32.05
      },
      {
        "pts": 6,
        "pct": 14.62
      },
      {
        "pts": 7,
        "pct": 8.94
      },
      {
        "pts": 8,
        "pct": 0
      },
      {
        "pts": 9,
        "pct": 0
      },
      {
        "pts": 10,
        "pct": 6.04
      }
    ]
  },
  "faction": null,
  "rosters": [
    {
      "player": "Dino",
      "avg": 8.4,
      "teams": [
        {
          "name": "Iran",
          "group": "G",
          "makeKo": 0,
          "qf": 0,
          "winCup": 0,
          "expPts": 0,
          "titleOdds": "OUT"
        },
        {
          "name": "Portugal",
          "group": "K",
          "makeKo": 100,
          "qf": 45,
          "winCup": 5.8,
          "expPts": 3.01,
          "titleOdds": "+1600"
        },
        {
          "name": "Canada",
          "group": "B",
          "makeKo": 100,
          "qf": 33.5,
          "winCup": 0.2,
          "expPts": 2.4,
          "titleOdds": "+42000"
        },
        {
          "name": "Morocco",
          "group": "C",
          "makeKo": 100,
          "qf": 66.5,
          "winCup": 2.3,
          "expPts": 2.96,
          "titleOdds": "+4200"
        }
      ]
    },
    {
      "player": "Rob",
      "avg": 8.4,
      "teams": [
        {
          "name": "Tunisia",
          "group": "F",
          "makeKo": 0,
          "qf": 0,
          "winCup": 0,
          "expPts": 0,
          "titleOdds": "OUT"
        },
        {
          "name": "Iraq",
          "group": "I",
          "makeKo": 0,
          "qf": 0,
          "winCup": 0,
          "expPts": 0,
          "titleOdds": "OUT"
        },
        {
          "name": "England",
          "group": "L",
          "makeKo": 100,
          "qf": 54.5,
          "winCup": 7.6,
          "expPts": 3.26,
          "titleOdds": "+1200"
        },
        {
          "name": "France",
          "group": "I",
          "makeKo": 100,
          "qf": 90.7,
          "winCup": 34.1,
          "expPts": 5.18,
          "titleOdds": "+195"
        }
      ]
    },
    {
      "player": "Max",
      "avg": 8.2,
      "teams": [
        {
          "name": "Norway",
          "group": "I",
          "makeKo": 100,
          "qf": 38.4,
          "winCup": 1.7,
          "expPts": 2.63,
          "titleOdds": "+5600"
        },
        {
          "name": "Ghana",
          "group": "L",
          "makeKo": 100,
          "qf": 14,
          "winCup": 0.1,
          "expPts": 1.49,
          "titleOdds": "+70000"
        },
        {
          "name": "United States",
          "group": "D",
          "makeKo": 100,
          "qf": 59.3,
          "winCup": 4.1,
          "expPts": 3.05,
          "titleOdds": "+2350"
        },
        {
          "name": "Senegal",
          "group": "I",
          "makeKo": 100,
          "qf": 0,
          "winCup": 0,
          "expPts": 1,
          "titleOdds": "OUT"
        }
      ]
    },
    {
      "player": "Nathan",
      "avg": 7.7,
      "teams": [
        {
          "name": "Argentina",
          "group": "J",
          "makeKo": 100,
          "qf": 73.5,
          "winCup": 19,
          "expPts": 4.09,
          "titleOdds": "+440"
        },
        {
          "name": "South Africa",
          "group": "A",
          "makeKo": 100,
          "qf": 0,
          "winCup": 0,
          "expPts": 1,
          "titleOdds": "OUT"
        },
        {
          "name": "Croatia",
          "group": "L",
          "makeKo": 100,
          "qf": 0,
          "winCup": 0,
          "expPts": 1,
          "titleOdds": "OUT"
        },
        {
          "name": "Egypt",
          "group": "G",
          "makeKo": 100,
          "qf": 9.5,
          "winCup": 0.1,
          "expPts": 1.65,
          "titleOdds": "+70000"
        }
      ]
    },
    {
      "player": "Nick",
      "avg": 5.6,
      "teams": [
        {
          "name": "Japan",
          "group": "F",
          "makeKo": 100,
          "qf": 0,
          "winCup": 0,
          "expPts": 1,
          "titleOdds": "OUT"
        },
        {
          "name": "DR Congo",
          "group": "K",
          "makeKo": 100,
          "qf": 0,
          "winCup": 0,
          "expPts": 1,
          "titleOdds": "OUT"
        },
        {
          "name": "Bosnia & Herzegovina",
          "group": "B",
          "makeKo": 100,
          "qf": 0,
          "winCup": 0,
          "expPts": 1,
          "titleOdds": "OUT"
        },
        {
          "name": "Belgium",
          "group": "G",
          "makeKo": 100,
          "qf": 40.7,
          "winCup": 1.4,
          "expPts": 2.62,
          "titleOdds": "+7200"
        }
      ]
    },
    {
      "player": "Jake",
      "avg": 5.5,
      "teams": [
        {
          "name": "Qatar",
          "group": "B",
          "makeKo": 0,
          "qf": 0,
          "winCup": 0,
          "expPts": 0,
          "titleOdds": "OUT"
        },
        {
          "name": "Switzerland",
          "group": "B",
          "makeKo": 100,
          "qf": 40.6,
          "winCup": 0.6,
          "expPts": 2.56,
          "titleOdds": "+16000"
        },
        {
          "name": "Mexico",
          "group": "A",
          "makeKo": 100,
          "qf": 45.5,
          "winCup": 5,
          "expPts": 2.97,
          "titleOdds": "+1900"
        },
        {
          "name": "New Zealand",
          "group": "G",
          "makeKo": 0,
          "qf": 0,
          "winCup": 0,
          "expPts": 0,
          "titleOdds": "OUT"
        }
      ]
    },
    {
      "player": "Kunal",
      "avg": 5.2,
      "teams": [
        {
          "name": "Germany",
          "group": "E",
          "makeKo": 100,
          "qf": 0,
          "winCup": 0,
          "expPts": 1,
          "titleOdds": "OUT"
        },
        {
          "name": "Brazil",
          "group": "C",
          "makeKo": 100,
          "qf": 61.6,
          "winCup": 6,
          "expPts": 3.24,
          "titleOdds": "+1550"
        },
        {
          "name": "South Korea",
          "group": "A",
          "makeKo": 0,
          "qf": 0,
          "winCup": 0,
          "expPts": 0,
          "titleOdds": "OUT"
        },
        {
          "name": "Netherlands",
          "group": "F",
          "makeKo": 100,
          "qf": 0,
          "winCup": 0,
          "expPts": 1,
          "titleOdds": "OUT"
        }
      ]
    },
    {
      "player": "Jack",
      "avg": 5.1,
      "teams": [
        {
          "name": "Colombia",
          "group": "K",
          "makeKo": 100,
          "qf": 45.5,
          "winCup": 2.4,
          "expPts": 2.48,
          "titleOdds": "+4000"
        },
        {
          "name": "Australia",
          "group": "D",
          "makeKo": 100,
          "qf": 9.4,
          "winCup": 0.1,
          "expPts": 1.64,
          "titleOdds": "+70000"
        },
        {
          "name": "Austria",
          "group": "J",
          "makeKo": 100,
          "qf": 0,
          "winCup": 0,
          "expPts": 1,
          "titleOdds": "OUT"
        },
        {
          "name": "Uruguay",
          "group": "H",
          "makeKo": 0,
          "qf": 0,
          "winCup": 0,
          "expPts": 0,
          "titleOdds": "OUT"
        }
      ]
    },
    {
      "player": "Adrian",
      "avg": 4.4,
      "teams": [
        {
          "name": "Sweden",
          "group": "F",
          "makeKo": 100,
          "qf": 0,
          "winCup": 0,
          "expPts": 1,
          "titleOdds": "OUT"
        },
        {
          "name": "Cape Verde",
          "group": "H",
          "makeKo": 100,
          "qf": 7.6,
          "winCup": 0.1,
          "expPts": 1.27,
          "titleOdds": "+70000"
        },
        {
          "name": "Paraguay",
          "group": "D",
          "makeKo": 100,
          "qf": 9.3,
          "winCup": 0.1,
          "expPts": 2.14,
          "titleOdds": "+70000"
        },
        {
          "name": "Jordan",
          "group": "J",
          "makeKo": 0,
          "qf": 0,
          "winCup": 0,
          "expPts": 0,
          "titleOdds": "OUT"
        }
      ]
    },
    {
      "player": "Dante",
      "avg": 3.3,
      "teams": [
        {
          "name": "Scotland",
          "group": "C",
          "makeKo": 0,
          "qf": 0,
          "winCup": 0,
          "expPts": 0,
          "titleOdds": "OUT"
        },
        {
          "name": "Spain",
          "group": "H",
          "makeKo": 100,
          "qf": 55,
          "winCup": 9.3,
          "expPts": 3.35,
          "titleOdds": "+960"
        },
        {
          "name": "Türkiye",
          "group": "D",
          "makeKo": 0,
          "qf": 0,
          "winCup": 0,
          "expPts": 0,
          "titleOdds": "OUT"
        },
        {
          "name": "Saudi Arabia",
          "group": "H",
          "makeKo": 0,
          "qf": 0,
          "winCup": 0,
          "expPts": 0,
          "titleOdds": "OUT"
        }
      ]
    },
    {
      "player": "Shaya",
      "avg": 3,
      "teams": [
        {
          "name": "Ecuador",
          "group": "E",
          "makeKo": 100,
          "qf": 0,
          "winCup": 0,
          "expPts": 1,
          "titleOdds": "OUT"
        },
        {
          "name": "Czechia",
          "group": "A",
          "makeKo": 0,
          "qf": 0,
          "winCup": 0,
          "expPts": 0,
          "titleOdds": "OUT"
        },
        {
          "name": "Ivory Coast",
          "group": "E",
          "makeKo": 100,
          "qf": 0,
          "winCup": 0,
          "expPts": 1,
          "titleOdds": "OUT"
        },
        {
          "name": "Algeria",
          "group": "J",
          "makeKo": 100,
          "qf": 0,
          "winCup": 0,
          "expPts": 1,
          "titleOdds": "OUT"
        }
      ]
    },
    {
      "player": "Matt",
      "avg": 0,
      "teams": [
        {
          "name": "Panama",
          "group": "L",
          "makeKo": 0,
          "qf": 0,
          "winCup": 0,
          "expPts": 0,
          "titleOdds": "OUT"
        },
        {
          "name": "Uzbekistan",
          "group": "K",
          "makeKo": 0,
          "qf": 0,
          "winCup": 0,
          "expPts": 0,
          "titleOdds": "OUT"
        },
        {
          "name": "Curaçao",
          "group": "E",
          "makeKo": 0,
          "qf": 0,
          "winCup": 0,
          "expPts": 0,
          "titleOdds": "OUT"
        },
        {
          "name": "Haiti",
          "group": "C",
          "makeKo": 0,
          "qf": 0,
          "winCup": 0,
          "expPts": 0,
          "titleOdds": "OUT"
        }
      ]
    }
  ]
}
